NEMO/__init__.py
NEMO/actions.py
NEMO/admin.py
NEMO/constants.py
NEMO/context_processors.py
NEMO/decorators.py
NEMO/evaluators.py
NEMO/exceptions.py
NEMO/fields.py
NEMO/forms.py
NEMO/interlocks.py
NEMO/log.py
NEMO/middleware.py
NEMO/migrations_utils.py
NEMO/mixins.py
NEMO/model_tree.py
NEMO/models.py
NEMO/parsers.py
NEMO/permissions.py
NEMO/policy.py
NEMO/properties_schemas.py
NEMO/provisioning.py
NEMO/rates.py
NEMO/rest_filter_backend.py
NEMO/rest_pagination.py
NEMO/serializers.py
NEMO/typing.py
NEMO/urls.py
NEMO/utilities.py
NEMO/validators.py
NEMO/wsgi.py
NEMO/apps/__init__.py
NEMO/apps/area_access/__init__.py
NEMO/apps/area_access/apps.py
NEMO/apps/area_access/urls.py
NEMO/apps/area_access/views.py
NEMO/apps/area_access/static/area_access/area_access.css
NEMO/apps/area_access/templates/area_access/already_logged_in.html
NEMO/apps/area_access/templates/area_access/badge_not_found.html
NEMO/apps/area_access/templates/area_access/base.html
NEMO/apps/area_access/templates/area_access/choose_area.html
NEMO/apps/area_access/templates/area_access/choose_project.html
NEMO/apps/area_access/templates/area_access/door_is_open.html
NEMO/apps/area_access/templates/area_access/farewell_screen.html
NEMO/apps/area_access/templates/area_access/inactive.html
NEMO/apps/area_access/templates/area_access/login_success.html
NEMO/apps/area_access/templates/area_access/logout_success.html
NEMO/apps/area_access/templates/area_access/logout_warning.html
NEMO/apps/area_access/templates/area_access/no_active_projects.html
NEMO/apps/area_access/templates/area_access/not_logged_in.html
NEMO/apps/area_access/templates/area_access/physical_access_denied.html
NEMO/apps/area_access/templates/area_access/resource_unavailable.html
NEMO/apps/area_access/templates/area_access/welcome_screen.html
NEMO/apps/kiosk/__init__.py
NEMO/apps/kiosk/apps.py
NEMO/apps/kiosk/urls.py
NEMO/apps/kiosk/views.py
NEMO/apps/kiosk/static/kiosk/kiosk.css
NEMO/apps/kiosk/templates/kiosk/acknowledgement.html
nemo-7.3.3.dist-info/licenses/LICENSE.md
nemo-7.3.3.dist-info/METADATA
nemo-7.3.3.dist-info/WHEEL
nemo-7.3.3.dist-info/entry_points.txt
nemo-7.3.3.dist-info/top_level.txt
nemo-7.3.3.dist-info/RECORD
