Metadata-Version: 2.4
Name: NEMO
Version: 7.3.3
Summary: NEMO is a laboratory logistics web application. Use it to schedule reservations, control tool access, track maintenance issues, and more.
Author-email: Center for Nanoscale Science and Technology <CNSTapplications@nist.gov>
Project-URL: Homepage, https://github.com/usnistgov/NEMO
Project-URL: Changelog, https://github.com/usnistgov/NEMO/releases
Project-URL: Issues, https://github.com/usnistgov/NEMO/issues
Keywords: NEMO
Classifier: Development Status :: 5 - Production/Stable
Classifier: Environment :: Web Environment
Classifier: Intended Audience :: Science/Research
Classifier: Intended Audience :: System Administrators
Classifier: License :: Public Domain
Classifier: Natural Language :: English
Classifier: Operating System :: OS Independent
Classifier: Framework :: Django :: 4.2
Classifier: Programming Language :: Python :: 3.10
Classifier: Programming Language :: Python :: 3.11
Classifier: Programming Language :: Python :: 3.12
Classifier: Programming Language :: Python :: 3.13
Requires-Python: <4,>=3.10
License-File: LICENSE.md
Requires-Dist: cryptography==46.0.3
Requires-Dist: Django==4.2.27
Requires-Dist: django-auditlog==3.4.1
Requires-Dist: django-filter==25.1
Requires-Dist: django-jsonform==2.23.2
Requires-Dist: django-mptt==0.18.0
Requires-Dist: djangorestframework==3.16.1
Requires-Dist: drf-excel==2.5.3
Requires-Dist: drf-flex-fields==1.0.2
Requires-Dist: fastjsonschema==2.21.2
Requires-Dist: ldap3==2.9.1
Requires-Dist: packaging==26.0
Requires-Dist: Pillow==12.1.0
Requires-Dist: pymodbus==3.11.4
Requires-Dist: python-dateutil==2.9.0
Requires-Dist: requests==2.32.5
Provides-Extra: dev-tools
Requires-Dist: pre-commit; extra == "dev-tools"
Requires-Dist: djlint; extra == "dev-tools"
Requires-Dist: black; extra == "dev-tools"
Dynamic: license-file
